README.md
pyproject.toml
setup.py
gocorn/__init__.py
gocorn/__main__.py
gocorn/gocorn.py
gocorn/message.py
gocorn/volk.py
gocorn/worker.py
gocorn/wsgi.py
gocorn.egg-info/PKG-INFO
gocorn.egg-info/SOURCES.txt
gocorn.egg-info/dependency_links.txt
gocorn.egg-info/requires.txt
gocorn.egg-info/top_level.txt